[
  { "id": 1, "option": "Alabama" },
  { "id": 2, "option": "Alaska" },
  { "id": 3, "option": "Arizona" },
  { "id": 4, "option": "Arkansas" },
  { "id": 5, "option": "California" },
  { "id": 6, "option": "Colorado" },
  { "id": 7, "option": "Connecticut" },
  { "id": 8, "option": "Delaware" },
  { "id": 9, "option": "Florida" },
  { "id": 10, "option": "Georgia" },
  { "id": 11, "option": "Hawaii" },
  { "id": 12, "option": "Idaho" },
  { "id": 13, "option": "Florida" },
  { "id": 14, "option": "Illinois" },
  { "id": 15, "option": "Indiana" },
  { "id": 16, "option": "Iowa" }
]
